pydantic_gitlab/__init__.py
pydantic_gitlab/artifacts.py
pydantic_gitlab/base.py
pydantic_gitlab/cache.py
pydantic_gitlab/default.py
pydantic_gitlab/environment.py
pydantic_gitlab/gitlab_ci.py
pydantic_gitlab/include.py
pydantic_gitlab/job.py
pydantic_gitlab/needs.py
pydantic_gitlab/pages.py
pydantic_gitlab/parallel.py
pydantic_gitlab/retry.py
pydantic_gitlab/rules.py
pydantic_gitlab/services.py
pydantic_gitlab/spec.py
pydantic_gitlab/trigger.py
pydantic_gitlab/variables.py
pydantic_gitlab/workflow.py
pydantic_gitlab/yaml_parser.py
pydantic_gitlab-0.2.5.dist-info/METADATA
pydantic_gitlab-0.2.5.dist-info/WHEEL
pydantic_gitlab-0.2.5.dist-info/licenses/LICENSE
pydantic_gitlab-0.2.5.dist-info/RECORD
