Metadata-Version: 2.4
Name: pydantic-gitlab
Version: 0.2.5
Summary: Pydantic models for parsing and validating GitLab CI/CD YAML configuration files
Project-URL: Homepage, https://github.com/johnlepikhin/pydantic-gitlab
Project-URL: Documentation, https://pydantic-gitlab.readthedocs.io
Project-URL: Repository, https://github.com/johnlepikhin/pydantic-gitlab
Project-URL: Issues, https://github.com/johnlepikhin/pydantic-gitlab/issues
Author-email: Evgenii Lepikhin <johnlepikhin@gmail.com>
License-Expression: MIT
License-File: LICENSE
Keywords: ci-cd,continuous-integration,devops,gitlab,gitlab-ci,gitlab-pipeline,parser,pydantic,type-safety,validation,yaml
Classifier: Development Status :: 3 - Alpha
Classifier: Intended Audience :: Developers
Classifier: License :: OSI Approved :: MIT License
Classifier: Programming Language :: Python :: 3
Classifier: Programming Language :: Python :: 3.9
Classifier: Programming Language :: Python :: 3.10
Classifier: Programming Language :: Python :: 3.11
Classifier: Programming Language :: Python :: 3.12
Requires-Python: >=3.9
Requires-Dist: pydantic>=2.0
Provides-Extra: dev
Requires-Dist: black>=23.0; extra == 'dev'
Requires-Dist: mypy>=1.0; extra == 'dev'
Requires-Dist: pre-commit>=3.0; extra == 'dev'
Requires-Dist: pytest-asyncio>=0.21; extra == 'dev'
Requires-Dist: pytest-cov>=4.0; extra == 'dev'
Requires-Dist: pytest>=7.0; extra == 'dev'
Requires-Dist: ruff>=0.1.0; extra == 'dev'
Requires-Dist: types-pyyaml>=6.0; extra == 'dev'
Provides-Extra: docs
Requires-Dist: mkdocs-material>=9.0; extra == 'docs'
Requires-Dist: mkdocs>=1.5; extra == 'docs'
Requires-Dist: mkdocstrings[python]>=0.20; extra == 'docs'
